{
  "Ads": [
    {
      "select_ads": "",
      "status_app": "0",
      "link_redirect": "https://",
      "admob_interid": "",
      "admob_nativeid": "",
      "admob_openid": "",
      "interval_intertitial": "5",
      "startappid": "",
      "fan_inter": "",
      "fan_banner_native": "",
      "mopub_banner": "",
      "mopub_inter": "",
      "unityID": "",
      "unity_inter": "",
      "unity_banner": "",
      "packagename": "com.adtwall.worldcupfootball"
    }
  ],
  "More":
  [
    
  ],

  "Categories": [
    {
      "id": 1,
      "name_category": "Argentina",
      "image": "https://i.pinimg.com/564x/6e/c7/af/6ec7afdd5fa1f5999208ea2045c472ef.jpg"

    },
	{
      "id": 2,
      "name_category": "Brazil",
      "image": "https://i.pinimg.com/564x/0c/88/86/0c88866150bd320ea52c000aa78015e2.jpg"

    },
	{
      "id": 3,
      "name_category": "Belgium",
      "image": "https://i.pinimg.com/564x/04/ca/8d/04ca8d3f0d8a517a5a3c4d9ffe43c939.jpg"

    },
	{
      "id": 4,
      "name_category": "Costa Rica",
      "image": "https://i.pinimg.com/564x/d4/df/25/d4df252bd4b1eef9d786448952cd9b3b.jpg"

    },
	{
      "id": 5,
      "name_category": "Croatia",
      "image": "https://i.pinimg.com/564x/ba/ca/8e/baca8e1251c0ad21f656cf0e23a632e3.jpg"

    },
	{
      "id": 6,
      "name_category": "England",
      "image": "https://i.pinimg.com/564x/36/b2/d6/36b2d60896ab797d300ffd0791e7fe11.jpg"

    },
	{
      "id": 7,
      "name_category": "Denmark",
      "image": "https://i.pinimg.com/564x/a3/5e/24/a35e2451d839b3e15c31952eedce87c6.jpg"

    },
	{
      "id": 8,
      "name_category": "France",
      "image": "https://i.pinimg.com/564x/92/22/af/9222af5121f34e36c1e121594a1d5d5a.jpg"

    },
    {
      "id": 9,
      "name_category": "German",
      "image": "https://i.pinimg.com/564x/1c/4e/34/1c4e34da0aa6bf43942de9bb47d1709d.jpg"

    },
	{
      "id": 10,
      "name_category": "Iran",
      "image": "https://i.pinimg.com/564x/94/9f/aa/949faa56258aaffe13c394de40d33e9f.jpg"

    },
	{
      "id": 11,
      "name_category": "Japan",
      "image": "https://i.pinimg.com/564x/69/7c/b2/697cb2399bcab319addc9b5552686f8a.jpg"

    },
	{
      "id": 12,
      "name_category": "Mexico",
      "image": "https://i.pinimg.com/564x/55/2a/ed/552aedb72939c331eee7ca38689f5bfc.jpg"

    },
	{
      "id": 13,
      "name_category": "Nigeria",
      "image": "https://i.pinimg.com/564x/38/39/76/383976cdc77b0716a99470ab360dd91d.jpg"

    },
	{
      "id": 14,
      "name_category": "Netherland",
      "image": "https://i.pinimg.com/564x/d6/96/41/d69641c5d11fa9986652e400f785022f.jpg"

    },
    {
      "id": 15,
      "name_category": "Senegal",
      "image": "https://i.pinimg.com/564x/78/13/1c/78131cdc381e976b8f7ccd1d1db7346f.jpg"

    },
    {
      "id": 16,
      "name_category": "Sweden",
      "image": "https://i.pinimg.com/564x/6b/08/8c/6b088c83d4830ac292fc85c94d52b575.jpg"

    },
	{
      "id": 17,
      "name_category": "South Korea",
      "image": "https://i.pinimg.com/564x/81/1a/1b/811a1bfa2a3ec78d4ef4e69a51836eb6.jpg"

    },
	{
      "id": 18,
      "name_category": "Uruguay",
      "image": "https://i.pinimg.com/564x/f3/9e/12/f39e12e76655cb617a98455a2943b4b3.jpg"

    }
  ],

  "Data":
  [
    {
      "id":1,
      "name_category": "Argentina",
      "title":"Argentina",
      "image":"https://i.pinimg.com/564x/6e/c7/af/6ec7afdd5fa1f5999208ea2045c472ef.jpg"
    },
	{
      "id":1,
      "name_category": "Argentina",
      "title":"Argentina",
      "image":"https://i.pinimg.com/564x/a7/97/40/a797406e051b4454462f95eaef2a4820.jpg"
    },
	{
      "id":1,
      "name_category": "Argentina",
      "title":"Argentina",
      "image":"https://i.pinimg.com/564x/ee/f1/57/eef157c3fe528dc2b07d8fc5d891a461.jpg"
    },
	{
      "id":1,
      "name_category": "Argentina",
      "title":"Argentina",
      "image":"https://i.pinimg.com/564x/7a/d1/33/7ad133d2dccca9ed670d5282193b954c.jpg"
    },
	{
      "id":1,
      "name_category": "Argentina",
      "title":"Argentina",
      "image":"https://i.pinimg.com/564x/cd/b5/87/cdb5875826bb5e739547e70b90f6ce07.jpg"
    },
	{
      "id":1,
      "name_category": "Argentina",
      "title":"Argentina",
      "image":"https://i.pinimg.com/564x/2e/eb/dc/2eebdc0af3c74bb578fb3e7c3c2f5417.jpg"
    },
	{
      "id":1,
      "name_category": "Argentina",
      "title":"Argentina",
      "image":"https://i.pinimg.com/564x/6e/7a/c4/6e7ac4ccaa96b6e8562bf2572ef61b94.jpg"
    },
	{
      "id":1,
      "name_category": "Argentina",
      "title":"Argentina",
      "image":"https://i.pinimg.com/564x/19/a9/c7/19a9c76bee19f2076d2d00459ba7a938.jpg"
    },
	{
      "id":1,
      "name_category": "Argentina",
      "title":"Argentina",
      "image":"https://i.pinimg.com/564x/cd/32/e4/cd32e409a7f465f45c60f254a02dc178.jpg"
    },
	{
      "id":1,
      "name_category": "Argentina",
      "title":"Argentina",
      "image":"https://i.pinimg.com/564x/54/80/a1/5480a17d4decb92b087ee61b54e42d59.jpg"
    },
	{
      "id":1,
      "name_category": "Argentina",
      "title":"Argentina",
      "image":"https://i.pinimg.com/564x/da/87/2e/da872e4ea7c48e105aa9aee64af181f8.jpg"
    },
	{
      "id":1,
      "name_category": "Argentina",
      "title":"Argentina",
      "image":"https://i.pinimg.com/564x/fd/1f/9e/fd1f9e6d23b8869f7de9777743663432.jpg"
    },
	{
      "id":1,
      "name_category": "Argentina",
      "title":"Argentina",
      "image":"https://i.pinimg.com/564x/ab/fe/d4/abfed42f0d385e2d58a3036e720c136e.jpg"
    },
	{
      "id":1,
      "name_category": "Argentina",
      "title":"Argentina",
      "image":"https://i.pinimg.com/564x/33/f1/13/33f113240792912aae73a7b379d749b9.jpg"
    },
	{
      "id":1,
      "name_category": "Argentina",
      "title":"Argentina",
      "image":"https://i.pinimg.com/564x/67/2d/98/672d98c86b48b1ed3e28ba0ba3cdfc74.jpg"
    },
	{
      "id":1,
      "name_category": "Argentina",
      "title":"Argentina",
      "image":"https://i.pinimg.com/564x/84/c3/82/84c382880fdb48c3f19593fea979a928.jpg"
    },
	{
      "id":1,
      "name_category": "Argentina",
      "title":"Argentina",
      "image":"https://i.pinimg.com/564x/10/3a/92/103a924e75b861f7a4f03a331042a446.jpg"
    },
	{
      "id":1,
      "name_category": "Argentina",
      "title":"Argentina",
      "image":"https://i.pinimg.com/564x/36/c5/02/36c502ddf79d39494964f972c1e51c16.jpg"
    },
	{
      "id":1,
      "name_category": "Argentina",
      "title":"Argentina",
      "image":"https://i.pinimg.com/564x/fb/9c/db/fb9cdbca3f548d1481789b3f643dd8a2.jpg"
    },
	{
      "id":1,
      "name_category": "Brazil",
      "title":"Brazil",
      "image":"https://i.pinimg.com/564x/0c/88/86/0c88866150bd320ea52c000aa78015e2.jpg"
    },
	{
      "id":1,
      "name_category": "Brazil",
      "title":"Brazil",
      "image":"https://i.pinimg.com/564x/d6/2e/96/d62e96a5a4ae68eaf82b2db98b85b50b.jpg"
    },
	{
      "id":1,
      "name_category": "Brazil",
      "title":"Brazil",
      "image":"https://i.pinimg.com/564x/be/c9/9b/bec99bb33eae0da3f643e337a4f4d6c8.jpg"
    },
	{
      "id":1,
      "name_category": "Brazil",
      "title":"Brazil",
      "image":"https://i.pinimg.com/564x/77/65/49/776549da701d4f42dcf24f4c38529da3.jpg"
    },
	{
      "id":1,
      "name_category": "Brazil",
      "title":"Brazil",
      "image":"https://i.pinimg.com/564x/cb/d8/e6/cbd8e675a41b439addbc538fd2c2157a.jpg"
    },
	{
      "id":1,
      "name_category": "Brazil",
      "title":"Brazil",
      "image":"https://i.pinimg.com/564x/da/af/1d/daaf1df9930dc82f231b47c7ce2d5ca5.jpg"
    },
	{
      "id":1,
      "name_category": "Brazil",
      "title":"Brazil",
      "image":"https://i.pinimg.com/564x/bb/f8/54/bbf854b66326aafee67e8c043fd6cf4c.jpg"
    },
	{
      "id":1,
      "name_category": "Brazil",
      "title":"Brazil",
      "image":"https://i.pinimg.com/564x/bb/c2/ba/bbc2ba1b3d716540a14edb283afbb38c.jpg"
    },
	{
      "id":1,
      "name_category": "Brazil",
      "title":"Brazil",
      "image":"https://i.pinimg.com/564x/88/fe/98/88fe98ba904cc84d00a5b7193299f04b.jpg"
    },
	{
      "id":1,
      "name_category": "Brazil",
      "title":"Brazil",
      "image":"https://i.pinimg.com/564x/ac/1b/b3/ac1bb357b035287724a59c48491a3cd9.jpg"
    },
	{
      "id":1,
      "name_category": "Brazil",
      "title":"Brazil",
      "image":"https://i.pinimg.com/564x/c4/72/9b/c4729bc91c24871ed5bd9cbe744ceb92.jpg"
    },
	{
      "id":1,
      "name_category": "Brazil",
      "title":"Brazil",
      "image":"https://i.pinimg.com/564x/19/fa/df/19fadf02ca845539342b36cd54ebacb8.jpg"
    },
	{
      "id":1,
      "name_category": "Brazil",
      "title":"Brazil",
      "image":"https://i.pinimg.com/564x/28/24/79/2824794c99bdacec726fdeefaf2e633d.jpg"
    },
	{
      "id":1,
      "name_category": "Brazil",
      "title":"Brazil",
      "image":"https://i.pinimg.com/564x/e7/a2/42/e7a24282442165e5a31761732da084ce.jpg"
    },
	{
      "id":1,
      "name_category": "Brazil",
      "title":"Brazil",
      "image":"https://i.pinimg.com/564x/c0/ca/6d/c0ca6d5ec9c3a780bbd5349f9884ed52.jpg"
    },
	{
      "id":1,
      "name_category": "Brazil",
      "title":"Brazil",
      "image":"https://i.pinimg.com/564x/55/e6/d4/55e6d43e8ca0544a0628c924a3c5c4a6.jpg"
    },
	{
      "id":1,
      "name_category": "Brazil",
      "title":"Brazil",
      "image":"https://i.pinimg.com/564x/7f/f2/96/7ff296f0e05ad3d8945ce31e6ede4279.jpg"
    },
	{
      "id":1,
      "name_category": "Brazil",
      "title":"Brazil",
      "image":"https://i.pinimg.com/564x/85/44/11/8544112e1452ce5a5b483c2e3823bfd9.jpg"
    },
	{
      "id":1,
      "name_category": "Brazil",
      "title":"Brazil",
      "image":"https://i.pinimg.com/564x/aa/9a/ab/aa9aab1f8e1765467246ddabab9cabd5.jpg"
    },
	{
      "id":1,
      "name_category": "Brazil",
      "title":"Brazil",
      "image":"https://i.pinimg.com/564x/cf/bd/2b/cfbd2bbeb523347a80f4f5b171da402f.jpg"
    },
	{
      "id":1,
      "name_category": "Belgium",
      "title":"Belgium",
      "image":"https://i.pinimg.com/564x/04/ca/8d/04ca8d3f0d8a517a5a3c4d9ffe43c939.jpg"
    },
	{
      "id":1,
      "name_category": "Belgium",
      "title":"Belgium",
      "image":"https://i.pinimg.com/564x/22/ef/83/22ef83e7660e5e1b3b17b5bd3bb0c2ee.jpg"
    },
	{
      "id":1,
      "name_category": "Belgium",
      "title":"Belgium",
      "image":"https://i.pinimg.com/564x/28/33/c9/2833c9c0a19d3d7f42fb669eefd75aad.jpg"
    },
	{
      "id":1,
      "name_category": "Belgium",
      "title":"Belgium",
      "image":"https://i.pinimg.com/236x/e0/45/9c/e0459cd6be985c55dd9b042d98e13a26.jpg"
    },
	{
      "id":1,
      "name_category": "Belgium",
      "title":"Belgium",
      "image":"https://i.pinimg.com/564x/41/9a/ea/419aea3c2fe4e2f962785f60a60d9277.jpg"
    },
	{
      "id":1,
      "name_category": "Belgium",
      "title":"Belgium",
      "image":"https://i.pinimg.com/564x/05/08/b2/0508b2764d9603e5339ba093a888f088.jpg"
    },
	{
      "id":1,
      "name_category": "Belgium",
      "title":"Belgium",
      "image":"https://i.pinimg.com/564x/9c/85/a5/9c85a5570374ea8471414c773275f6b8.jpg"
    },
	{
      "id":1,
      "name_category": "Belgium",
      "title":"Belgium",
      "image":"https://i.pinimg.com/564x/b6/d1/20/b6d12097d89cf5c9c1719cf294da97de.jpg"
    },
	{
      "id":1,
      "name_category": "Belgium",
      "title":"Belgium",
      "image":"https://i.pinimg.com/564x/72/40/9a/72409a961bf59bd4b4c12b92713583df.jpg"
    },
	{
      "id":1,
      "name_category": "Belgium",
      "title":"Belgium",
      "image":"https://i.pinimg.com/564x/5c/04/68/5c0468ec6a4f0fde60941452c7aae8a0.jpg"
    },
	{
      "id":1,
      "name_category": "Belgium",
      "title":"Belgium",
      "image":"https://i.pinimg.com/564x/e3/f8/c6/e3f8c6a29dd0521ac36054e5e0cc808e.jpg"
    },
	{
      "id":1,
      "name_category": "Belgium",
      "title":"Belgium",
      "image":"https://i.pinimg.com/564x/11/57/3a/11573aaff9a2990bb10d3732d38e337d.jpg"
    },
	{
      "id":1,
      "name_category": "Belgium",
      "title":"Belgium",
      "image":"https://i.pinimg.com/564x/f2/23/84/f223840f59ca23d1764b3d94ddf9e92c.jpg"
    },
	{
      "id":1,
      "name_category": "Belgium",
      "title":"Belgium",
      "image":"https://i.pinimg.com/564x/88/40/3b/88403bff0e20d200e4deb33357446905.jpg"
    },
	{
      "id":1,
      "name_category": "Belgium",
      "title":"Belgium",
      "image":"https://i.pinimg.com/564x/7c/c8/a2/7cc8a240db92be82a43e5fe4b928e15e.jpg"
    },
	{
      "id":1,
      "name_category": "Belgium",
      "title":"Belgium",
      "image":"https://i.pinimg.com/564x/de/25/9b/de259b408a4eda43a65dcb358078ef65.jpg"
    },
	{
      "id":1,
      "name_category": "Belgium",
      "title":"Belgium",
      "image":"https://i.pinimg.com/564x/33/f8/f5/33f8f57f8d183ffdbfab57a7adeea26f.jpg"
    },
	{
      "id":1,
      "name_category": "Belgium",
      "title":"Belgium",
      "image":"https://i.pinimg.com/564x/5b/49/05/5b4905a3f110f0f1192e1199eccf428b.jpg"
    },
	{
      "id":1,
      "name_category": "Belgium",
      "title":"Belgium",
      "image":"https://i.pinimg.com/564x/b3/04/9d/b3049dd13bf7d7bd2ea5284ca0c65eab.jpg"
    },
	{
      "id":1,
      "name_category": "Belgium",
      "title":"Belgium",
      "image":"https://i.pinimg.com/564x/cd/61/bb/cd61bb598b114eb911f9f220dc4d4ec8.jpg"
    },
	{
      "id":1,
      "name_category": "Costa Rica",
      "title":"Costa Rica",
      "image":"https://i.pinimg.com/564x/9e/17/90/9e17903d16e81e245c2ce527f9bace09.jpg"
    },
	{
      "id":1,
      "name_category": "Costa Rica",
      "title":"Costa Rica",
      "image":"https://i.pinimg.com/564x/d4/df/25/d4df252bd4b1eef9d786448952cd9b3b.jpg"
    },
	{
      "id":1,
      "name_category": "Costa Rica",
      "title":"Costa Rica",
      "image":"https://i.pinimg.com/564x/11/1a/13/111a13319898e8420e01a64c92980b91.jpg"
    },
	{
      "id":1,
      "name_category": "Costa Rica",
      "title":"Costa Rica",
      "image":"https://i.pinimg.com/564x/68/d0/9d/68d09d8027cc151e6d8aa1a0f73e4554.jpg"
    },
	{
      "id":1,
      "name_category": "Costa Rica",
      "title":"Costa Rica",
      "image":"https://i.pinimg.com/564x/11/e4/f9/11e4f9335313d8b5eb0357cfbaa42a0a.jpg"
    },
	{
      "id":1,
      "name_category": "Costa Rica",
      "title":"Costa Rica",
      "image":"https://i.pinimg.com/564x/d7/f4/1f/d7f41fbfc126a81aafe2f23a22222039.jpg"
    },
	{
      "id":1,
      "name_category": "Costa Rica",
      "title":"Costa Rica",
      "image":"https://i.pinimg.com/564x/35/fb/38/35fb380e283a9782a0f52e13b28427c6.jpg"
    },
	{
      "id":1,
      "name_category": "Costa Rica",
      "title":"Costa Rica",
      "image":"https://i.pinimg.com/564x/13/9b/1f/139b1f0f58fa18a2cde1b21740f4220a.jpg"
    },
	{
      "id":1,
      "name_category": "Costa Rica",
      "title":"Costa Rica",
      "image":"https://i.pinimg.com/564x/27/97/86/279786623b08a86a33d597a39f6cbcac.jpg"
    },
	{
      "id":1,
      "name_category": "Costa Rica",
      "title":"Costa Rica",
      "image":"https://i.pinimg.com/564x/70/94/a2/7094a2748b7514550fafc870d162e2f7.jpg"
    },
	{
      "id":1,
      "name_category": "Costa Rica",
      "title":"Costa Rica",
      "image":"https://i.pinimg.com/564x/fe/f2/07/fef20741627f1cd61183d9d94993f029.jpg"
    },
	{
      "id":1,
      "name_category": "Croatia",
      "title":"Croatia",
      "image":"https://i.pinimg.com/564x/ba/ca/8e/baca8e1251c0ad21f656cf0e23a632e3.jpg"
    },
	{
      "id":1,
      "name_category": "Croatia",
      "title":"Croatia",
      "image":"https://i.pinimg.com/564x/66/54/39/665439047db9c339c06d4709d1e98a00.jpg"
    },
	{
      "id":1,
      "name_category": "Croatia",
      "title":"Croatia",
      "image":"https://i.pinimg.com/564x/5d/66/c1/5d66c1b9ef3846500693d46e46265e98.jpg"
    },
	{
      "id":1,
      "name_category": "Croatia",
      "title":"Croatia",
      "image":"https://i.pinimg.com/564x/ab/c3/fd/abc3fd4b3f88888fd011e48f732c0f7a.jpg"
    },
	{
      "id":1,
      "name_category": "Croatia",
      "title":"Croatia",
      "image":"https://i.pinimg.com/564x/0c/17/62/0c176210101296480d113d626df8135f.jpg"
    },
	{
      "id":1,
      "name_category": "Croatia",
      "title":"Croatia",
      "image":"https://i.pinimg.com/564x/4c/fe/f4/4cfef4c0e9ba7e0a9c738ae643700f8a.jpg"
    },
	{
      "id":1,
      "name_category": "Croatia",
      "title":"Croatia",
      "image":"https://i.pinimg.com/564x/2f/b2/18/2fb218e91d9e5e204ad624098acb0f6b.jpg"
    },
	{
      "id":1,
      "name_category": "Croatia",
      "title":"Croatia",
      "image":"https://i.pinimg.com/564x/99/07/78/9907786752cf76fc049e9acdc916255a.jpg"
    },
	{
      "id":1,
      "name_category": "Croatia",
      "title":"Croatia",
      "image":"https://i.pinimg.com/564x/82/ac/bd/82acbd857055ac7eb361a6d711a4d51b.jpg"
    },
	{
      "id":1,
      "name_category": "Croatia",
      "title":"Croatia",
      "image":"https://i.pinimg.com/564x/7f/38/42/7f384275080f3a8855224755dc1d8180.jpg"
    },
	{
      "id":1,
      "name_category": "Croatia",
      "title":"Croatia",
      "image":"https://i.pinimg.com/564x/fd/6f/85/fd6f855166e14adb6ae01463ecbb4db2.jpg"
    },
	{
      "id":1,
      "name_category": "Croatia",
      "title":"Croatia",
      "image":"https://i.pinimg.com/564x/73/d3/40/73d3402726cda4bc1235634cbd69b8dd.jpg"
    },
	{
      "id":1,
      "name_category": "Croatia",
      "title":"Croatia",
      "image":"https://i.pinimg.com/564x/79/32/5c/79325c3efa15952a9844cef50aab240a.jpg"
    },
	{
      "id":1,
      "name_category": "Croatia",
      "title":"Croatia",
      "image":"https://i.pinimg.com/564x/b2/16/73/b21673f7473c10b536ac0f376de4daf8.jpg"
    },
	{
      "id":1,
      "name_category": "Croatia",
      "title":"Croatia",
      "image":"https://i.pinimg.com/564x/72/c9/97/72c99799fe89d9c6310a74f34f16e396.jpg"
    },
	{
      "id":1,
      "name_category": "Croatia",
      "title":"Croatia",
      "image":"https://i.pinimg.com/564x/c7/02/04/c70204fe7d199e463a37085711c2fdf7.jpg"
    },
	{
      "id":1,
      "name_category": "Croatia",
      "title":"Croatia",
      "image":"https://i.pinimg.com/564x/ab/d7/5a/abd75a8bf10ad814b50a1e2dd93e9ce5.jpg"
    },
	{
      "id":1,
      "name_category": "England",
      "title":"England",
      "image":"https://i.pinimg.com/564x/36/b2/d6/36b2d60896ab797d300ffd0791e7fe11.jpg"
    },
	{
      "id":1,
      "name_category": "England",
      "title":"England",
      "image":"https://i.pinimg.com/564x/70/df/6a/70df6a45c49cc69541fb6d220a955ed5.jpg"
    },
	{
      "id":1,
      "name_category": "England",
      "title":"England",
      "image":"https://i.pinimg.com/564x/18/b3/19/18b319930383d43015003d8900b0f32b.jpg"
    },
	{
      "id":1,
      "name_category": "England",
      "title":"England",
      "image":"https://i.pinimg.com/564x/e4/cc/db/e4ccdb04887fe43368d279deef21a615.jpg"
    },
	{
      "id":1,
      "name_category": "England",
      "title":"England",
      "image":"https://i.pinimg.com/564x/67/50/5d/67505d3c4446502a2dcfaa60e1828fc0.jpg"
    },
	{
      "id":1,
      "name_category": "England",
      "title":"England",
      "image":"https://i.pinimg.com/564x/ac/d2/8c/acd28c99d8d7846d21309f5833f16708.jpg"
    },
	{
      "id":1,
      "name_category": "England",
      "title":"England",
      "image":"https://i.pinimg.com/564x/44/03/cb/4403cbe80e88974cecd2a2d4449ad801.jpg"
    },
	{
      "id":1,
      "name_category": "England",
      "title":"England",
      "image":"https://i.pinimg.com/750x/2a/f4/a3/2af4a36eba9fc7d551cd5b18446c67d5.jpg"
    },
	{
      "id":1,
      "name_category": "England",
      "title":"England",
      "image":"https://i.pinimg.com/564x/2b/91/be/2b91be144abe849187608a0e52b1fe75.jpg"
    },
	{
      "id":1,
      "name_category": "England",
      "title":"England",
      "image":"https://i.pinimg.com/750x/69/6a/48/696a486c2a14b2c5924cf35bbb360779.jpg"
    },
	{
      "id":1,
      "name_category": "England",
      "title":"England",
      "image":"https://i.pinimg.com/564x/aa/d8/ec/aad8ec6aa968cb521906ee0fed4f0e91.jpg"
    },
	{
      "id":1,
      "name_category": "England",
      "title":"England",
      "image":"https://i.pinimg.com/564x/4d/65/7c/4d657c99df9d8e8af61e25d9644294fa.jpg"
    },
	{
      "id":1,
      "name_category": "England",
      "title":"England",
      "image":"https://i.pinimg.com/564x/58/30/87/5830879f1f5b2719ed22ae8fc1cf5199.jpg"
    },
	{
      "id":1,
      "name_category": "England",
      "title":"England",
      "image":"https://i.pinimg.com/564x/fe/a3/d3/fea3d3adad8b8ce30605e4821c79c4fb.jpg"
    },
	{
      "id":1,
      "name_category": "England",
      "title":"England",
      "image":"https://i.pinimg.com/564x/53/14/f7/5314f740bda84f77dbcef11b37a650cf.jpg"
    },
	{
      "id":1,
      "name_category": "England",
      "title":"England",
      "image":"https://i.pinimg.com/564x/cc/d3/b3/ccd3b31a1a83fe7ba982120be2168048.jpg"
    },
	{
      "id":1,
      "name_category": "England",
      "title":"England",
      "image":"https://i.pinimg.com/564x/78/30/55/783055ce4a27ccc55a7fb6a1a09e43a8.jpg"
    },
	{
      "id":1,
      "name_category": "England",
      "title":"England",
      "image":"https://i.pinimg.com/564x/68/2c/e9/682ce9982bfef3256852821c290af49d.jpg"
    },
	{
      "id":1,
      "name_category": "England",
      "title":"England",
      "image":"https://i.pinimg.com/564x/3f/33/23/3f33233257add132fed50969c2e124ef.jpg"
    },
	{
      "id":1,
      "name_category": "England",
      "title":"England",
      "image":"https://i.pinimg.com/564x/aa/0a/22/aa0a22b1320f4f38db80115e3c74138b.jpg"
    },
	{
      "id":1,
      "name_category": "Denmark",
      "title":"Denmark",
      "image":"https://i.pinimg.com/564x/a3/5e/24/a35e2451d839b3e15c31952eedce87c6.jpg"
    },
	{
      "id":1,
      "name_category": "Denmark",
      "title":"Denmark",
      "image":"https://i.pinimg.com/564x/f6/46/b8/f646b8517dcf8f1dde5220ce9168d1b2.jpg"
    },
	{
      "id":1,
      "name_category": "Denmark",
      "title":"Denmark",
      "image":"https://i.pinimg.com/564x/28/62/45/28624568a941257f8b37bd81ddea5fde.jpg"
    },
	{
      "id":1,
      "name_category": "Denmark",
      "title":"Denmark",
      "image":"https://i.pinimg.com/564x/ba/c3/94/bac39423c745d5695b9caa486ac42936.jpg"
    },
	{
      "id":1,
      "name_category": "Denmark",
      "title":"Denmark",
      "image":"https://i.pinimg.com/564x/f0/87/fc/f087fccad9ae83ff071e9a97c81b4494.jpg"
    },
	{
      "id":1,
      "name_category": "Denmark",
      "title":"Denmark",
      "image":"https://i.pinimg.com/564x/79/d8/c0/79d8c0d2949f8c705d83862520522d24.jpg"
    },
	{
      "id":1,
      "name_category": "Denmark",
      "title":"Denmark",
      "image":"https://i.pinimg.com/564x/67/14/2a/67142adeb229f78c2f1753e95481f817.jpg"
    },
	{
      "id":1,
      "name_category": "Denmark",
      "title":"Denmark",
      "image":"https://i.pinimg.com/564x/8a/11/fa/8a11faf968f8947fcf10f32c650d8081.jpg"
    },
	{
      "id":1,
      "name_category": "Denmark",
      "title":"Denmark",
      "image":"https://i.pinimg.com/564x/55/e2/16/55e216db95406b8dacbe124a47451906.jpg"
    },
	{
      "id":1,
      "name_category": "Denmark",
      "title":"Denmark",
      "image":"https://i.pinimg.com/564x/43/64/1a/43641ae5aa02ff1c1c82020c177bc7dc.jpg"
    },
	{
      "id":1,
      "name_category": "Denmark",
      "title":"Denmark",
      "image":"https://i.pinimg.com/564x/b3/9a/03/b39a032831211fdb937f2a5afd820d8f.jpg"
    },
	{
      "id":1,
      "name_category": "Denmark",
      "title":"Denmark",
      "image":"https://i.pinimg.com/564x/b9/48/f2/b948f2cdf78c2ee1aa66284d33f6e37b.jpg"
    },
	{
      "id":1,
      "name_category": "France",
      "title":"France",
      "image":"https://i.pinimg.com/564x/92/22/af/9222af5121f34e36c1e121594a1d5d5a.jpg"
    },
	{
      "id":1,
      "name_category": "France",
      "title":"France",
      "image":"https://i.pinimg.com/564x/03/8b/39/038b39b311afe9b1e29bca5ad8220f98.jpg"
    },
	{
      "id":1,
      "name_category": "France",
      "title":"France",
      "image":"https://i.pinimg.com/564x/25/62/4d/25624dfb960c7be28ad64590aeab5b2e.jpg"
    },
	{
      "id":1,
      "name_category": "France",
      "title":"France",
      "image":"https://i.pinimg.com/564x/5f/ea/23/5fea23d489b85731327c0344939633eb.jpg"
    },
	{
      "id":1,
      "name_category": "France",
      "title":"France",
      "image":"https://i.pinimg.com/564x/15/4a/ec/154aec6eff8af20753999b8b762240bb.jpg"
    },
	{
      "id":1,
      "name_category": "France",
      "title":"France",
      "image":"https://i.pinimg.com/564x/37/55/4c/37554c81718b626744d28ddcb7e3da3d.jpg"
    },
	{
      "id":1,
      "name_category": "France",
      "title":"France",
      "image":"https://i.pinimg.com/564x/5b/47/8b/5b478b2cf0fdcfba2b1c31a50e88f8e6.jpg"
    },
	{
      "id":1,
      "name_category": "France",
      "title":"France",
      "image":"https://i.pinimg.com/564x/17/05/e2/1705e29060298a1c03a10dc7bcea77a7.jpg"
    },
	{
      "id":1,
      "name_category": "France",
      "title":"France",
      "image":"https://i.pinimg.com/564x/d9/78/8b/d9788b4b3569f49c4868878043904a58.jpg"
    },
	{
      "id":1,
      "name_category": "France",
      "title":"France",
      "image":"https://i.pinimg.com/564x/b5/42/bb/b542bbf98249a0244cb98e17de1a1afc.jpg"
    },
	{
      "id":1,
      "name_category": "France",
      "title":"France",
      "image":"https://i.pinimg.com/564x/fe/67/83/fe678320e06c7aee52decb4fd40a7520.jpg"
    },
	{
      "id":1,
      "name_category": "France",
      "title":"France",
      "image":"https://i.pinimg.com/564x/43/a9/58/43a958ad5930330e9d0fd6aab6bfcf5a.jpg"
    },
	{
      "id":1,
      "name_category": "France",
      "title":"France",
      "image":"https://i.pinimg.com/564x/32/bb/92/32bb923bdea176cfdd0f2f008d3d791b.jpg"
    },
	{
      "id":1,
      "name_category": "France",
      "title":"France",
      "image":"https://i.pinimg.com/564x/6d/d4/79/6dd4799bf18e044458ee5ad5e92997ba.jpg"
    },
	{
      "id":1,
      "name_category": "France",
      "title":"France",
      "image":"https://i.pinimg.com/564x/98/2a/31/982a31b8e895a74d0111fec07879a761.jpg"
    },
	{
      "id":1,
      "name_category": "France",
      "title":"France",
      "image":"https://i.pinimg.com/564x/70/68/82/706882d16c901d0b1373d8834a9cf731.jpg"
    },
	{
      "id":1,
      "name_category": "France",
      "title":"France",
      "image":"https://i.pinimg.com/564x/35/2c/8f/352c8fec1fec19f9ce3f4befafb70532.jpg"
    },
	{
      "id":1,
      "name_category": "France",
      "title":"France",
      "image":"https://i.pinimg.com/564x/7c/39/62/7c3962f3e38e7b8889ddb8b805def638.jpg"
    },
	{
      "id":1,
      "name_category": "France",
      "title":"France",
      "image":"https://i.pinimg.com/564x/24/82/ff/2482ffeaf1ebb62fec73561c87047d60.jpg"
    },
	{
      "id":1,
      "name_category": "France",
      "title":"France",
      "image":"https://i.pinimg.com/564x/71/2d/cb/712dcbe8748738e9f26c32f2acf601d3.jpg"
    },
	{
      "id":1,
      "name_category": "German",
      "title":"German",
      "image":"https://i.pinimg.com/564x/1c/4e/34/1c4e34da0aa6bf43942de9bb47d1709d.jpg"
    },
	{
      "id":1,
      "name_category": "German",
      "title":"German",
      "image":"https://i.pinimg.com/564x/16/c6/20/16c6202c84a9cb49b9f6e517ee31a5c0.jpg"
    },
	{
      "id":1,
      "name_category": "German",
      "title":"German",
      "image":"https://i.pinimg.com/564x/a2/58/a2/a258a28a392ea5dde957465be7c55fae.jpg"
    },
	{
      "id":1,
      "name_category": "German",
      "title":"German",
      "image":"https://i.pinimg.com/564x/7e/73/c1/7e73c150821b096720d34a3c8372f307.jpg"
    },
	{
      "id":1,
      "name_category": "German",
      "title":"German",
      "image":"https://i.pinimg.com/564x/b6/c9/d7/b6c9d73f0b590420ce6ab8f3ad5d2208.jpg"
    },
	{
      "id":1,
      "name_category": "German",
      "title":"German",
      "image":"https://i.pinimg.com/564x/68/46/cd/6846cd6bb9098bb70830f52b5cca9b1e.jpg"
    },
	{
      "id":1,
      "name_category": "German",
      "title":"German",
      "image":"https://i.pinimg.com/564x/5b/bb/c9/5bbbc9cc7a5c92cc47f52c93b0a59688.jpg"
    },
	{
      "id":1,
      "name_category": "German",
      "title":"German",
      "image":"https://i.pinimg.com/564x/85/89/4d/85894da67fc35212670f325c557445c9.jpg"
    },
	{
      "id":1,
      "name_category": "German",
      "title":"German",
      "image":"https://i.pinimg.com/564x/31/cf/8a/31cf8a85155818183715a2e2fa3749b1.jpg"
    },
	{
      "id":1,
      "name_category": "German",
      "title":"German",
      "image":"https://i.pinimg.com/564x/5f/cd/a2/5fcda200708116bab32efc7693b62626.jpg"
    },
	{
      "id":1,
      "name_category": "German",
      "title":"German",
      "image":"https://i.pinimg.com/564x/62/08/09/620809adec0a7d7d54d0ae7aea2ce02e.jpg"
    },
	{
      "id":1,
      "name_category": "German",
      "title":"German",
      "image":"https://i.pinimg.com/564x/8f/3f/08/8f3f08c0d6a9841c05226d23b7be3288.jpg"
    },
	{
      "id":1,
      "name_category": "German",
      "title":"German",
      "image":"https://i.pinimg.com/564x/5c/5d/64/5c5d64c83a510c338c5372e266141d75.jpg"
    },
	{
      "id":1,
      "name_category": "German",
      "title":"German",
      "image":"https://i.pinimg.com/564x/39/15/7a/39157a301fc4bf1f86797483016cc992.jpg"
    },
	{
      "id":1,
      "name_category": "German",
      "title":"German",
      "image":"https://i.pinimg.com/564x/8e/fe/5c/8efe5ccd459a89de798d3f44d51f8385.jpg"
    },
	{
      "id":1,
      "name_category": "German",
      "title":"German",
      "image":"https://i.pinimg.com/564x/49/8e/57/498e576120bd149fbf36f5cd87620865.jpg"
    },
	{
      "id":1,
      "name_category": "German",
      "title":"German",
      "image":"https://i.pinimg.com/564x/24/f3/7d/24f37de8caff678ff4361c37e74604a8.jpg"
    },
	{
      "id":1,
      "name_category": "German",
      "title":"German",
      "image":"https://i.pinimg.com/564x/0f/86/d9/0f86d9ebe31c3fa4999704b1afea68d4.jpg"
    },
	{
      "id":1,
      "name_category": "German",
      "title":"German",
      "image":"https://i.pinimg.com/564x/f0/eb/89/f0eb89afb5e3e012c20918a301873417.jpg"
    },
	{
      "id":1,
      "name_category": "German",
      "title":"German",
      "image":"https://i.pinimg.com/564x/dc/91/71/dc9171d7be965bf9aa546d7d0715aea4.jpg"
    },
	{
      "id":1,
      "name_category": "German",
      "title":"German",
      "image":"https://i.pinimg.com/564x/58/74/bf/5874bf3c5275114b66e6b486c4de48df.jpg"
    },
	{
      "id":1,
      "name_category": "German",
      "title":"German",
      "image":"https://i.pinimg.com/564x/ff/25/3c/ff253c8356085ca9ecd9056faa036c71.jpg"
    },
	{
      "id":1,
      "name_category": "Iran",
      "title":"Iran",
      "image":"https://i.pinimg.com/564x/94/9f/aa/949faa56258aaffe13c394de40d33e9f.jpg"
    },
	{
      "id":1,
      "name_category": "Iran",
      "title":"Iran",
      "image":"https://i.pinimg.com/564x/9a/73/7e/9a737ec646c87a804409d688aea440e0.jpg"
    },
	{
      "id":1,
      "name_category": "Iran",
      "title":"Iran",
      "image":"https://i.pinimg.com/564x/12/96/5f/12965f7e2c30af3a05019d2ceca8ffd6.jpg"
    },
	{
      "id":1,
      "name_category": "Iran",
      "title":"Iran",
      "image":"https://i.pinimg.com/564x/7e/a1/ba/7ea1ba6d81b7d93cacf34d3d9f1300a2.jpg"
    },
	{
      "id":1,
      "name_category": "Iran",
      "title":"Iran",
      "image":"https://i.pinimg.com/564x/e5/7f/d4/e57fd4474ab4bcecad0e176a5addfa83.jpg"
    },
	{
      "id":1,
      "name_category": "Iran",
      "title":"Iran",
      "image":"https://i.pinimg.com/564x/6d/e5/33/6de533f7f5fb86a68ffddfd65fa70092.jpg"
    },
	{
      "id":1,
      "name_category": "Iran",
      "title":"Iran",
      "image":"https://i.pinimg.com/564x/f1/d4/69/f1d4699d041ee799f0379e91e7bf600a.jpg"
    },
	{
      "id":1,
      "name_category": "Iran",
      "title":"Iran",
      "image":"https://i.pinimg.com/564x/a2/e8/7f/a2e87fbc0a5566494066bca391a2a561.jpg"
    },
	{
      "id":1,
      "name_category": "Iran",
      "title":"Iran",
      "image":"https://i.pinimg.com/564x/62/f4/9a/62f49a81d6e0795ef9e33de334fe5de7.jpg"
    },
	{
      "id":1,
      "name_category": "Japan",
      "title":"titleImage",
      "image":"https://i.pinimg.com/564x/69/7c/b2/697cb2399bcab319addc9b5552686f8a.jpg"
    },
	{
      "id":1,
      "name_category": "Japan",
      "title":"Japan",
      "image":"https://i.pinimg.com/564x/65/49/f1/6549f15f2f408532d1fc7b52803b0ade.jpg"
    },
	{
      "id":1,
      "name_category": "Japan",
      "title":"Japan",
      "image":"https://i.pinimg.com/564x/61/56/b7/6156b7520ccc62dfdf1a5fb584349c99.jpg"
    },
	{
      "id":1,
      "name_category": "Japan",
      "title":"Japan",
      "image":"https://i.pinimg.com/564x/5b/31/b0/5b31b0f8d5a275304fd58c885966092d.jpg"
    },
	{
      "id":1,
      "name_category": "Japan",
      "title":"Japan",
      "image":"https://i.pinimg.com/564x/94/5d/3c/945d3c67bed412e87aedd71067ed4323.jpg"
    },
	{
      "id":1,
      "name_category": "Japan",
      "title":"Japan",
      "image":"https://i.pinimg.com/564x/01/7c/78/017c784a2acb450cffa464310327a98b.jpg"
    },
	{
      "id":1,
      "name_category": "Japan",
      "title":"Japan",
      "image":"https://i.pinimg.com/564x/5b/fb/0e/5bfb0ecf244f8b165030bbb39b7b812f.jpg"
    },
	{
      "id":1,
      "name_category": "Japan",
      "title":"Japan",
      "image":"https://i.pinimg.com/564x/80/53/56/805356176d07ba999d9285844097fce9.jpg"
    },
	{
      "id":1,
      "name_category": "Japan",
      "title":"Japan",
      "image":"https://i.pinimg.com/564x/34/00/9c/34009cb085ddda412291356e98461ffc.jpg"
    },
	{
      "id":1,
      "name_category": "Japan",
      "title":"Japan",
      "image":"https://i.pinimg.com/564x/e6/ff/80/e6ff80e6d0438fcce5d1846ca429a911.jpg"
    },
	{
      "id":1,
      "name_category": "Japan",
      "title":"Japan",
      "image":"https://i.pinimg.com/564x/dc/a3/9a/dca39a79db6ac3352e7cb0543dc222d9.jpg"
    },
	{
      "id":1,
      "name_category": "Japan",
      "title":"Japan",
      "image":"https://i.pinimg.com/564x/4f/a8/f5/4fa8f5d7ec3fb00bde47e1942d308726.jpg"
    },
	{
      "id":1,
      "name_category": "Japan",
      "title":"Japan",
      "image":"https://i.pinimg.com/564x/fc/1a/dd/fc1addf2e1a1ca3a73020440c9becfbd.jpg"
    },
	{
      "id":1,
      "name_category": "Mexico",
      "title":"Mexico",
      "image":"https://i.pinimg.com/564x/55/2a/ed/552aedb72939c331eee7ca38689f5bfc.jpg"
    },
	{
      "id":1,
      "name_category": "Mexico",
      "title":"Mexico",
      "image":"https://i.pinimg.com/564x/02/87/62/028762d8abf8526a5df115a9901e52a6.jpg"
    },
	{
      "id":1,
      "name_category": "Mexico",
      "title":"Mexico",
      "image":"https://i.pinimg.com/564x/94/04/7f/94047fd090fdb8ac1f14ab0cd19bc2fe.jpg"
    },
	{
      "id":1,
      "name_category": "Mexico",
      "title":"Mexico",
      "image":"https://i.pinimg.com/564x/ca/de/d8/caded81f58f7c6b5c455b2abbab56f73.jpg"
    },
	{
      "id":1,
      "name_category": "Mexico",
      "title":"Mexico",
      "image":"https://i.pinimg.com/564x/a2/b7/e8/a2b7e8c4d3c2496d9eb89c82679bcea9.jpg"
    },
	{
      "id":1,
      "name_category": "Mexico",
      "title":"Mexico",
      "image":"https://i.pinimg.com/564x/20/7d/a6/207da653d999d89f2e15964d28c1180d.jpg"
    },
	{
      "id":1,
      "name_category": "Mexico",
      "title":"Mexico",
      "image":"https://i.pinimg.com/564x/98/ae/40/98ae4087b06aef4fef0bfd3a1100599a.jpg"
    },
	{
      "id":1,
      "name_category": "Mexico",
      "title":"Mexico",
      "image":"https://i.pinimg.com/564x/fc/f0/b0/fcf0b0c326e720940c4998e3e6aa874b.jpg"
    },
	{
      "id":1,
      "name_category": "Mexico",
      "title":"Mexico",
      "image":"https://i.pinimg.com/564x/5d/e6/20/5de62013c7a93698c7c9ad5ad01901d2.jpg"
    },
	{
      "id":1,
      "name_category": "Mexico",
      "title":"Mexico",
      "image":"https://i.pinimg.com/564x/4e/e6/a8/4ee6a81e5d17422580426b9599c673c7.jpg"
    },
	{
      "id":1,
      "name_category": "Mexico",
      "title":"Mexico",
      "image":"https://i.pinimg.com/564x/a6/2c/2b/a62c2b8b41e820ef36e054e7803ea86a.jpg"
    },
	{
      "id":1,
      "name_category": "Mexico",
      "title":"Mexico",
      "image":"https://i.pinimg.com/564x/a4/06/3d/a4063dd91521508c287e9de34bd9e7e8.jpg"
    },
	{
      "id":1,
      "name_category": "Mexico",
      "title":"Mexico",
      "image":"https://i.pinimg.com/564x/3a/06/bd/3a06bdff6b12d80c14f72cd31563f0f8.jpg"
    },
	{
      "id":1,
      "name_category": "Mexico",
      "title":"Mexico",
      "image":"https://i.pinimg.com/564x/b1/91/f2/b191f2c51acfaef9cbe13c8aa4eb763b.jpg"
    },
	{
      "id":1,
      "name_category": "Mexico",
      "title":"Mexico",
      "image":"https://i.pinimg.com/564x/da/f6/58/daf658bb039c99018e94dcbf3aa9d6d8.jpg"
    },
	{
      "id":1,
      "name_category": "Nigeria",
      "title":"Nigeria",
      "image":"https://i.pinimg.com/564x/38/39/76/383976cdc77b0716a99470ab360dd91d.jpg"
    },
	{
      "id":1,
      "name_category": "Nigeria",
      "title":"Nigeria",
      "image":"https://i.pinimg.com/564x/c3/c2/89/c3c2899bd9aefed0704dc1dea2e2465d.jpg"
    },
	{
      "id":1,
      "name_category": "Nigeria",
      "title":"Nigeria",
      "image":"https://i.pinimg.com/564x/51/42/1a/51421ab7d19060a4c4dcbf69dd71c8fe.jpg"
    },
	{
      "id":1,
      "name_category": "Nigeria",
      "title":"Nigeria",
      "image":"https://i.pinimg.com/564x/05/ae/66/05ae6607fdd79d3679c4eba1d8555b32.jpg"
    },
	{
      "id":1,
      "name_category": "Nigeria",
      "title":"Nigeria",
      "image":"https://i.pinimg.com/564x/f9/65/65/f9656587f9404f011bf82ce640277d24.jpg"
    },
	{
      "id":1,
      "name_category": "Nigeria",
      "title":"Nigeria",
      "image":"https://i.pinimg.com/564x/80/ff/da/80ffda6ae3b7c0fe19bf3ddf90422804.jpg"
    },
	{
      "id":1,
      "name_category": "Nigeria",
      "title":"Nigeria",
      "image":"https://i.pinimg.com/564x/22/66/69/226669a0620753addf04857bff4f26f4.jpg"
    },
	{
      "id":1,
      "name_category": "Nigeria",
      "title":"Nigeria",
      "image":"https://i.pinimg.com/564x/bf/f2/2e/bff22eb678837abe73c7d2c5aeb8a14b.jpg"
    },
	{
      "id":1,
      "name_category": "Nigeria",
      "title":"Nigeria",
      "image":"https://i.pinimg.com/564x/81/39/0e/81390ebeb5a970b94fbdddd55ade86b8.jpg"
    },
	{
      "id":1,
      "name_category": "Netherland",
      "title":"Netherland",
      "image":"https://i.pinimg.com/564x/d6/96/41/d69641c5d11fa9986652e400f785022f.jpg"
    },
	{
      "id":1,
      "name_category": "Netherland",
      "title":"Netherland",
      "image":"https://i.pinimg.com/564x/9e/cf/e5/9ecfe5784d49757014d23650106cdfd1.jpg"
    },
	{
      "id":1,
      "name_category": "Netherland",
      "title":"Netherland",
      "image":"https://i.pinimg.com/564x/4e/24/17/4e2417203c05657d40d8650313f6a701.jpg"
    },
	{
      "id":1,
      "name_category": "Netherland",
      "title":"Netherland",
      "image":"https://i.pinimg.com/564x/0a/58/ef/0a58ef64029fe5d49e86855423145897.jpg"
    },
	{
      "id":1,
      "name_category": "Netherland",
      "title":"Netherland",
      "image":"https://i.pinimg.com/564x/40/72/75/407275e34fe976fa66039bbc4385c43f.jpg"
    },
	{
      "id":1,
      "name_category": "Netherland",
      "title":"Netherland",
      "image":"https://i.pinimg.com/564x/36/90/30/36903027d3d1a98b807f206ab53f891d.jpg"
    },
	{
      "id":1,
      "name_category": "Netherland",
      "title":"Netherland",
      "image":"https://i.pinimg.com/564x/ae/53/66/ae5366b53053f0397b5f80f80243bd4e.jpg"
    },
	{
      "id":1,
      "name_category": "Netherland",
      "title":"Netherland",
      "image":"https://i.pinimg.com/564x/8a/d8/05/8ad805f80e8988e4f8c8cb16f9c692da.jpg"
    },
	{
      "id":1,
      "name_category": "Netherland",
      "title":"Netherland",
      "image":"https://i.pinimg.com/564x/c3/99/b8/c399b8ab5bd98ef49e0fe28d67d0b308.jpg"
    },
	{
      "id":1,
      "name_category": "Netherland",
      "title":"Netherland",
      "image":"https://i.pinimg.com/564x/85/96/5b/85965b370a037822d5d5568e81b5496d.jpg"
    },
	{
      "id":1,
      "name_category": "Netherland",
      "title":"Netherland",
      "image":"https://i.pinimg.com/564x/0f/fd/81/0ffd8160569231d3b3d89e598e55a680.jpg"
    },
	{
      "id":1,
      "name_category": "Netherland",
      "title":"Netherland",
      "image":"https://i.pinimg.com/564x/5b/4e/b3/5b4eb3d3a9ff9c9ad4576a31c66eefb4.jpg"
    },
	{
      "id":1,
      "name_category": "Netherland",
      "title":"Netherland",
      "image":"https://i.pinimg.com/564x/72/8e/71/728e71257bc4be4f5c4c845b9d50ab30.jpg"
    },
	{
      "id":1,
      "name_category": "Netherland",
      "title":"Netherland",
      "image":"https://i.pinimg.com/564x/85/c0/ff/85c0ff1f4d1036cc4aff888bb7f6cf0a.jpg"
    },
	{
      "id":1,
      "name_category": "Netherland",
      "title":"Netherland",
      "image":"https://i.pinimg.com/564x/25/12/7f/25127f0be194004791997f7862c51d20.jpg"
    },
	{
      "id":1,
      "name_category": "Netherland",
      "title":"Netherland",
      "image":"https://i.pinimg.com/564x/85/de/c3/85dec30774986f728ec1189d47005713.jpg"
    },
	{
      "id":1,
      "name_category": "Netherland",
      "title":"Netherland",
      "image":"https://i.pinimg.com/564x/fa/46/b4/fa46b4c67ea95e7171d089e69a68a347.jpg"
    },
	{
      "id":1,
      "name_category": "Netherland",
      "title":"Netherland",
      "image":"https://i.pinimg.com/564x/c3/7e/b4/c37eb4d8e34b40ec0102b87da38bb608.jpg"
    },
	{
      "id":1,
      "name_category": "Netherland",
      "title":"Netherland",
      "image":"https://i.pinimg.com/564x/98/68/94/98689448b08467a1df4b748ff0442544.jpg"
    },
	{
      "id":1,
      "name_category": "Netherland",
      "title":"Netherland",
      "image":"https://i.pinimg.com/564x/cb/62/cf/cb62cfae6a9764c2880eb06d40fea249.jpg"
    },
	{
      "id":1,
      "name_category": "Netherland",
      "title":"Netherland",
      "image":"https://i.pinimg.com/564x/af/c3/26/afc3264038bd9d65e17b31a49075151b.jpg"
    },
	{
      "id":1,
      "name_category": "Netherland",
      "title":"Netherland",
      "image":"https://i.pinimg.com/564x/93/41/5b/93415bf5514f382c364c88526a67627d.jpg"
    },
	{
      "id":1,
      "name_category": "Senegal",
      "title":"Senegal",
      "image":"https://i.pinimg.com/564x/78/13/1c/78131cdc381e976b8f7ccd1d1db7346f.jpg"
    },
	{
      "id":1,
      "name_category": "Senegal",
      "title":"Senegal",
      "image":"https://i.pinimg.com/564x/ff/6a/5d/ff6a5d16b871a620ad2cb78ad0fa3782.jpg"
    },
	{
      "id":1,
      "name_category": "Senegal",
      "title":"Senegal",
      "image":"https://i.pinimg.com/564x/2f/c0/63/2fc063f7ab72eb1bf3500221073104cc.jpg"
    },
	{
      "id":1,
      "name_category": "Senegal",
      "title":"Senegal",
      "image":"https://i.pinimg.com/564x/44/2e/06/442e063d13ea03621c9780f0f7badad2.jpg"
    },
	{
      "id":1,
      "name_category": "Senegal",
      "title":"Senegal",
      "image":"https://i.pinimg.com/564x/33/f5/b3/33f5b3be986784b9a2f0a1d4e814dec7.jpg"
    },
	{
      "id":1,
      "name_category": "Senegal",
      "title":"Senegal",
      "image":"https://i.pinimg.com/564x/1e/e3/d0/1ee3d0d02f855153e068d9977e8a8bea.jpg"
    },
	{
      "id":1,
      "name_category": "Senegal",
      "title":"Senegal",
      "image":"https://i.pinimg.com/564x/70/29/30/70293055f24e9b7021f0626fc8e14a19.jpg"
    },
	{
      "id":1,
      "name_category": "Senegal",
      "title":"Senegal",
      "image":"https://i.pinimg.com/564x/b6/9c/1b/b69c1b5a592a86d3f02f557b14ff5baa.jpg"
    },
	{
      "id":1,
      "name_category": "Senegal",
      "title":"Senegal",
      "image":"https://i.pinimg.com/564x/47/45/56/474556555cbbcbcd831bfdafdc8aee8e.jpg"
    },
	{
      "id":1,
      "name_category": "Senegal",
      "title":"Senegal",
      "image":"https://i.pinimg.com/564x/b1/1a/fe/b11afe03c348b30edf178aed6fe72774.jpg"
    },
	{
      "id":1,
      "name_category": "Sweden",
      "title":"Sweden",
      "image":"https://i.pinimg.com/564x/6b/08/8c/6b088c83d4830ac292fc85c94d52b575.jpg"
    },
	{
      "id":1,
      "name_category": "Sweden",
      "title":"Sweden",
      "image":"https://i.pinimg.com/564x/4f/26/2b/4f262b1e75124aec37288454cdd35077.jpg"
    },
	{
      "id":1,
      "name_category": "Sweden",
      "title":"Sweden",
      "image":"https://i.pinimg.com/564x/96/4e/26/964e2641966ba31fbedb1275631e6141.jpg"
    },
	{
      "id":1,
      "name_category": "Sweden",
      "title":"Sweden",
      "image":"https://i.pinimg.com/564x/77/6c/f9/776cf90c39ca9644a2b5495bbc952626.jpg"
    },
	{
      "id":1,
      "name_category": "Sweden",
      "title":"Sweden",
      "image":"https://i.pinimg.com/564x/54/85/46/548546b7fc13f6c88664ad41c6959697.jpg"
    },
	{
      "id":1,
      "name_category": "Sweden",
      "title":"Sweden",
      "image":"https://i.pinimg.com/564x/c8/90/3c/c8903c2b02136091a29bd01dd5af8124.jpg"
    },
	{
      "id":1,
      "name_category": "Sweden",
      "title":"Sweden",
      "image":"https://i.pinimg.com/564x/3f/6f/b7/3f6fb7c83fb4535bfe5c9c946fae7d96.jpg"
    },
	{
      "id":1,
      "name_category": "Sweden",
      "title":"Sweden",
      "image":"https://i.pinimg.com/564x/63/09/f8/6309f8eff9ff9fe201bf6376f6e9de3b.jpg"
    },
	{
      "id":1,
      "name_category": "Sweden",
      "title":"Sweden",
      "image":"https://i.pinimg.com/236x/ba/6a/74/ba6a74f8fd05a1c902e6b8330a6a08f5.jpg"
    },
	{
      "id":1,
      "name_category": "Sweden",
      "title":"Sweden",
      "image":"https://i.pinimg.com/564x/6c/50/f2/6c50f24ed35bf97bcb644fcb7fea3217.jpg"
    },
	{
      "id":1,
      "name_category": "Sweden",
      "title":"Sweden",
      "image":"https://i.pinimg.com/564x/e1/39/e7/e139e74632ca8708001181f80d4fe0da.jpg"
    },
	{
      "id":1,
      "name_category": "Sweden",
      "title":"Sweden",
      "image":"https://i.pinimg.com/564x/dd/d8/1a/ddd81aa810efe900ba1149645afe773b.jpg"
    },
	{
      "id":1,
      "name_category": "Sweden",
      "title":"Sweden",
      "image":"https://i.pinimg.com/564x/7c/71/76/7c717694daef8f7ea2722990cba5841e.jpg"
    },
	{
      "id":1,
      "name_category": "Sweden",
      "title":"Sweden",
      "image":"https://i.pinimg.com/564x/ce/98/63/ce986359af7aa66ecc6d76ba001d4fc2.jpg"
    },
	{
      "id":1,
      "name_category": "South Korea",
      "title":"South Korea",
      "image":"https://i.pinimg.com/564x/81/1a/1b/811a1bfa2a3ec78d4ef4e69a51836eb6.jpg"
    },
	{
      "id":1,
      "name_category": "South Korea",
      "title":"South Korea",
      "image":"https://i.pinimg.com/564x/70/5a/0d/705a0d8cd230a8fbb6f66505f0128dcd.jpg"
    },
	{
      "id":1,
      "name_category": "South Korea",
      "title":"South Korea",
      "image":"https://i.pinimg.com/564x/2e/f2/b1/2ef2b1e031486cc0956248598caae8ca.jpg"
    },
	{
      "id":1,
      "name_category": "South Korea",
      "title":"South Korea",
      "image":"https://i.pinimg.com/564x/57/ee/c4/57eec4a270935417270d1ff095e3f43b.jpg"
    },
	{
      "id":1,
      "name_category": "South Korea",
      "title":"South Korea",
      "image":"https://i.pinimg.com/564x/8d/19/43/8d19436d200131f8cfc817a75b516d29.jpg"
    },
	{
      "id":1,
      "name_category": "South Korea",
      "title":"South Korea",
      "image":"https://i.pinimg.com/564x/e0/bf/d1/e0bfd123e1ab59da2056266ea41f5330.jpg"
    },
	{
      "id":1,
      "name_category": "South Korea",
      "title":"South Korea",
      "image":"https://i.pinimg.com/564x/09/42/f7/0942f71b551c7a485b14bdab8b46a79d.jpg"
    },
	{
      "id":1,
      "name_category": "South Korea",
      "title":"South Korea",
      "image":"https://i.pinimg.com/564x/e9/a9/0d/e9a90d192adbd37b9193c47222aa02e6.jpg"
    },
	{
      "id":1,
      "name_category": "South Korea",
      "title":"South Korea",
      "image":"https://i.pinimg.com/564x/ba/1b/4a/ba1b4a0fe26697720b7585d2b9abea0a.jpg"
    },
	{
      "id":1,
      "name_category": "Uruguay",
      "title":"Uruguay",
      "image":"https://i.pinimg.com/564x/f3/9e/12/f39e12e76655cb617a98455a2943b4b3.jpg"
    },
	{
      "id":1,
      "name_category": "Uruguay",
      "title":"Uruguay",
      "image":"https://i.pinimg.com/564x/96/7e/84/967e84beb313d7f41a46612c152f5877.jpg"
    },
	{
      "id":1,
      "name_category": "Uruguay",
      "title":"Uruguay",
      "image":"https://i.pinimg.com/564x/31/0b/cc/310bccfcb81878e5c8ec2e11a55dbe0f.jpg"
    },
	{
      "id":1,
      "name_category": "Uruguay",
      "title":"Uruguay",
      "image":"https://i.pinimg.com/564x/6d/25/0e/6d250e0dd9381251ca7c1be1ef9fd976.jpg"
    },
	{
      "id":1,
      "name_category": "Uruguay",
      "title":"Uruguay",
      "image":"https://i.pinimg.com/564x/de/48/8a/de488a34568045f547e087567f8941d3.jpg"
    },
	{
      "id":1,
      "name_category": "Uruguay",
      "title":"Uruguay",
      "image":"https://i.pinimg.com/564x/26/4d/4f/264d4ff20794b3e19d1962b75ec38811.jpg"
    },
	{
      "id":1,
      "name_category": "Uruguay",
      "title":"Uruguay",
      "image":"https://i.pinimg.com/564x/cc/14/3d/cc143dbdab2ee6791f2ef5c7eba7e0d1.jpg"
    },
	{
      "id":1,
      "name_category": "Uruguay",
      "title":"Uruguay",
      "image":"https://i.pinimg.com/564x/0c/b8/62/0cb862f103a311a2b242e0e3ccb71d6d.jpg"
    },
	{
      "id":1,
      "name_category": "Uruguay",
      "title":"Uruguay",
      "image":"https://i.pinimg.com/564x/f0/87/f0/f087f026c439e1fed5ea68ed3e54484d.jpg"
    },
	{
      "id":1,
      "name_category": "Uruguay",
      "title":"Uruguay",
      "image":"https://i.pinimg.com/564x/74/ff/ba/74ffba5418a077c99703c4b0c17e4f44.jpg"
    },
	{
      "id":1,
      "name_category": "Uruguay",
      "title":"Uruguay",
      "image":"https://i.pinimg.com/564x/06/7f/77/067f771a63e9ed3174a98292f7209fe9.jpg"
    },
	{
      "id":1,
      "name_category": "Uruguay",
      "title":"Uruguay",
      "image":"https://i.pinimg.com/564x/de/08/40/de0840879c21dbd04839893b4dd4f6c7.jpg"
    },
	{
      "id":1,
      "name_category": "Uruguay",
      "title":"Uruguay",
      "image":"https://i.pinimg.com/564x/be/03/1c/be031c13b23f5dbfd61320e9eb6a7f4c.jpg"
    },
	{
      "id":1,
      "name_category": "Uruguay",
      "title":"Uruguay",
      "image":"https://i.pinimg.com/564x/13/fb/96/13fb96264f13ee33f41d919abd919d96.jpg"
    },
	{
      "id":1,
      "name_category": "Uruguay",
      "title":"Uruguay",
      "image":"https://i.pinimg.com/564x/dc/ec/0a/dcec0a082b5a43f68f171d7c9efe526c.jpg"
    },
	{
      "id":1,
      "name_category": "Uruguay",
      "title":"Uruguay",
      "image":"https://i.pinimg.com/564x/f3/83/2f/f3832f829ace78d46049a6b53027b50d.jpg"
    },
	{
      "id":1,
      "name_category": "Uruguay",
      "title":"Uruguay",
      "image":"https://i.pinimg.com/564x/6f/bf/45/6fbf45e1bcf612b9a285e607506c5d34.jpg"
    },
	{
      "id":1,
      "name_category": "Uruguay",
      "title":"Uruguay",
      "image":"https://i.pinimg.com/564x/53/ca/58/53ca58d5fea87b604015f30ca2bc21ec.jpg"
    }
   
  ]
}
